setup.py
hello_world_amit.egg-info/PKG-INFO
hello_world_amit.egg-info/SOURCES.txt
hello_world_amit.egg-info/dependency_links.txt
hello_world_amit.egg-info/not-zip-safe
hello_world_amit.egg-info/top_level.txt
try_pypi/__init__.py