Metadata-Version: 1.0
Name: hello-world-amit
Version: 0.1
Summary: Hello world
Home-page: https://github.com/karnikamit/try_pypi.git
Author: karnikamit
Author-email: karnikamit46@gmail.com
License: MIT
Platform: UNKNOWN
